README.md
setup.cfg
setup.py
jupyter_manim/__init__.py
jupyter_manim.egg-info/PKG-INFO
jupyter_manim.egg-info/SOURCES.txt
jupyter_manim.egg-info/dependency_links.txt
jupyter_manim.egg-info/requires.txt
jupyter_manim.egg-info/top_level.txt