Metadata-Version: 1.1
Name: jupyter-manim
Version: 0.11
Summary: Cell magic rendering displaying videos in Jupyter/IPython
Home-page: https://github.com/krassowski/jupyter-manim
Author: Michal Krassowski
Author-email: krassowski.michal+pypi@gmail.com
License: MIT
Download-URL: https://github.com/krassowski/jupyter-manim/tarball/v0.1
Keywords: jupyter,jupyterlab,notebook,manim,manimlib
Platform: UNKNOWN
Classifier: Development Status :: 4 - Beta
Classifier: License :: OSI Approved :: MIT License
Classifier: Framework :: IPython
Classifier: Framework :: Jupyter
Classifier: Operating System :: Microsoft :: Windows
Classifier: Operating System :: POSIX :: Linux
Classifier: Topic :: Utilities
Classifier: Topic :: Software Development :: User Interfaces
Classifier: Topic :: Software Development :: Libraries :: Python Modules
Classifier: Intended Audience :: Developers
Classifier: Intended Audience :: Science/Research
Classifier: Programming Language :: Python :: 3.6
Classifier: Programming Language :: Python :: 3.7
